{
 "custom_fields": [
  {
   "_assign": null,
   "_comments": null,
   "_liked_by": null,
   "_user_tags": null,
   "allow_in_quick_entry": 0,
   "allow_on_submit": 1,
   "bold": 0,
   "collapsible": 0,
   "collapsible_depends_on": null,
   "columns": 0,
   "creation": "2021-01-08 18:03:26.232446",
   "default": null,
   "depends_on": null,
   "description": null,
   "docstatus": 0,
   "dt": "Stock Entry Detail",
   "fetch_from": "item_code.gst_hsn_code",
   "fetch_if_empty": 0,
   "fieldname": "gst_hsn_code",
   "fieldtype": "Data",
   "hidden": 0,
   "hide_border": 0,
   "hide_days": 0,
   "hide_seconds": 0,
   "idx": 20,
   "ignore_user_permissions": 0,
   "ignore_xss_filter": 0,
   "in_global_search": 0,
   "in_list_view": 0,
   "in_preview": 0,
   "in_standard_filter": 0,
   "insert_after": "description",
   "label": "HSN/SAC",
   "length": 0,
   "mandatory_depends_on": null,
   "modified": "2019-07-15 13:12:13.635464",
   "modified_by": "Administrator",
   "name": "Stock Entry Detail-gst_hsn_code",
   "no_copy": 0,
   "non_negative": 0,
   "options": null,
   "owner": "Administrator",
   "parent": null,
   "parentfield": null,
   "parenttype": null,
   "permlevel": 0,
   "precision": "",
   "print_hide": 0,
   "print_hide_if_no_value": 0,
   "print_width": null,
   "read_only": 0,
   "read_only_depends_on": null,
   "report_hide": 0,
   "reqd": 0,
   "search_index": 0,
   "translatable": 1,
   "unique": 0,
   "width": null
  },
  {
   "_assign": null,
   "_comments": null,
   "_liked_by": null,
   "_user_tags": null,
   "allow_in_quick_entry": 0,
   "allow_on_submit": 0,
   "bold": 0,
   "collapsible": 0,
   "collapsible_depends_on": null,
   "columns": 0,
   "creation": "2021-01-08 18:05:06.506753",
   "default": null,
   "depends_on": null,
   "description": null,
   "docstatus": 0,
   "dt": "Stock Entry Detail",
   "fetch_from": null,
   "fetch_if_empty": 0,
   "fieldname": "bom",
   "fieldtype": "Link",
   "hidden": 0,
   "hide_border": 0,
   "hide_days": 0,
   "hide_seconds": 0,
   "idx": 52,
   "ignore_user_permissions": 0,
   "ignore_xss_filter": 0,
   "in_global_search": 0,
   "in_list_view": 0,
   "in_preview": 0,
   "in_standard_filter": 0,
   "insert_after": "branch",
   "label": "BOM",
   "length": 0,
   "mandatory_depends_on": null,
   "modified": "2020-04-10 16:47:32.806743",
   "modified_by": "Administrator",
   "name": "Stock Entry Detail-bom",
   "no_copy": 0,
   "non_negative": 0,
   "options": "BOM",
   "owner": "Administrator",
   "parent": null,
   "parentfield": null,
   "parenttype": null,
   "permlevel": 0,
   "precision": "",
   "print_hide": 0,
   "print_hide_if_no_value": 0,
   "print_width": null,
   "read_only": 0,
   "read_only_depends_on": null,
   "report_hide": 0,
   "reqd": 0,
   "search_index": 0,
   "translatable": 0,
   "unique": 0,
   "width": null
  },
  {
   "_assign": null,
   "_comments": null,
   "_liked_by": null,
   "_user_tags": null,
   "allow_in_quick_entry": 0,
   "allow_on_submit": 0,
   "bold": 0,
   "collapsible": 0,
   "collapsible_depends_on": null,
   "columns": 0,
   "creation": "2021-01-08 18:05:04.145238",
   "default": null,
   "depends_on": null,
   "description": null,
   "docstatus": 0,
   "dt": "Stock Entry Detail",
   "fetch_from": null,
   "fetch_if_empty": 0,
   "fieldname": "branch",
   "fieldtype": "Link",
   "hidden": 0,
   "hide_border": 0,
   "hide_days": 0,
   "hide_seconds": 0,
   "idx": 51,
   "ignore_user_permissions": 0,
   "ignore_xss_filter": 0,
   "in_global_search": 0,
   "in_list_view": 0,
   "in_preview": 0,
   "in_standard_filter": 0,
   "insert_after": "accounting_dimensions_section",
   "label": "Branch",
   "length": 0,
   "mandatory_depends_on": null,
   "modified": "2020-05-20 18:57:38.549966",
   "modified_by": "Administrator",
   "name": "Stock Entry Detail-branch",
   "no_copy": 0,
   "non_negative": 0,
   "options": "Branch",
   "owner": "Administrator",
   "parent": null,
   "parentfield": null,
   "parenttype": null,
   "permlevel": 0,
   "precision": "",
   "print_hide": 0,
   "print_hide_if_no_value": 0,
   "print_width": null,
   "read_only": 0,
   "read_only_depends_on": null,
   "report_hide": 0,
   "reqd": 0,
   "search_index": 0,
   "translatable": 0,
   "unique": 0,
   "width": null
  },
  {
   "_assign": null,
   "_comments": null,
   "_liked_by": null,
   "_user_tags": null,
   "allow_in_quick_entry": 0,
   "allow_on_submit": 0,
   "bold": 0,
   "collapsible": 0,
   "collapsible_depends_on": null,
   "columns": 0,
   "creation": "2021-01-08 18:05:22.014931",
   "default": null,
   "depends_on": null,
   "description": null,
   "docstatus": 0,
   "dt": "Stock Entry Detail",
   "fetch_from": null,
   "fetch_if_empty": 0,
   "fieldname": "patient",
   "fieldtype": "Link",
   "hidden": 0,
   "hide_border": 0,
   "hide_days": 0,
   "hide_seconds": 0,
   "idx": 69,
   "ignore_user_permissions": 0,
   "ignore_xss_filter": 0,
   "in_global_search": 0,
   "in_list_view": 0,
   "in_preview": 0,
   "in_standard_filter": 0,
   "insert_after": "po_detail",
   "label": "Patient",
   "length": 0,
   "mandatory_depends_on": null,
   "modified": "2020-10-26 12:03:05.172076",
   "modified_by": "Administrator",
   "name": "Stock Entry Detail-patient",
   "no_copy": 0,
   "non_negative": 0,
   "options": "Patient",
   "owner": "Administrator",
   "parent": null,
   "parentfield": null,
   "parenttype": null,
   "permlevel": 0,
   "precision": "",
   "print_hide": 0,
   "print_hide_if_no_value": 0,
   "print_width": null,
   "read_only": 1,
   "read_only_depends_on": null,
   "report_hide": 0,
   "reqd": 0,
   "search_index": 0,
   "translatable": 0,
   "unique": 0,
   "width": null
  },
  {
   "_assign": null,
   "_comments": null,
   "_liked_by": null,
   "_user_tags": null,
   "allow_in_quick_entry": 0,
   "allow_on_submit": 0,
   "bold": 0,
   "collapsible": 0,
   "collapsible_depends_on": null,
   "columns": 0,
   "creation": "2021-01-08 18:05:24.304500",
   "default": null,
   "depends_on": null,
   "description": null,
   "docstatus": 0,
   "dt": "Stock Entry Detail",
   "fetch_from": null,
   "fetch_if_empty": 0,
   "fieldname": "inpatient_medication_entry_child",
   "fieldtype": "Data",
   "hidden": 0,
   "hide_border": 0,
   "hide_days": 0,
   "hide_seconds": 0,
   "idx": 70,
   "ignore_user_permissions": 0,
   "ignore_xss_filter": 0,
   "in_global_search": 0,
   "in_list_view": 0,
   "in_preview": 0,
   "in_standard_filter": 0,
   "insert_after": "patient",
   "label": "Inpatient Medication Entry Child",
   "length": 0,
   "mandatory_depends_on": null,
   "modified": "2020-10-26 12:03:05.552149",
   "modified_by": "Administrator",
   "name": "Stock Entry Detail-inpatient_medication_entry_child",
   "no_copy": 0,
   "non_negative": 0,
   "options": null,
   "owner": "Administrator",
   "parent": null,
   "parentfield": null,
   "parenttype": null,
   "permlevel": 0,
   "precision": "",
   "print_hide": 0,
   "print_hide_if_no_value": 0,
   "print_width": null,
   "read_only": 1,
   "read_only_depends_on": null,
   "report_hide": 0,
   "reqd": 0,
   "search_index": 0,
   "translatable": 1,
   "unique": 0,
   "width": null
  },
  {
   "_assign": null,
   "_comments": null,
   "_liked_by": null,
   "_user_tags": null,
   "allow_in_quick_entry": 0,
   "allow_on_submit": 0,
   "bold": 0,
   "collapsible": 0,
   "collapsible_depends_on": null,
   "columns": 0,
   "creation": "2021-01-08 18:04:54.555130",
   "default": null,
   "depends_on": "eval:in_list([\"Material Receipt\", \"Manufacture\"], parent.purpose)",
   "description": null,
   "docstatus": 0,
   "dt": "Stock Entry Detail",
   "fetch_from": null,
   "fetch_if_empty": 0,
   "fieldname": "supplier_bag_no",
   "fieldtype": "Data",
   "hidden": 0,
   "hide_border": 0,
   "hide_days": 0,
   "hide_seconds": 0,
   "idx": 46,
   "ignore_user_permissions": 0,
   "ignore_xss_filter": 0,
   "in_global_search": 0,
   "in_list_view": 0,
   "in_preview": 0,
   "in_standard_filter": 0,
   "insert_after": "col_break4",
   "label": "Supplier Bag No.",
   "length": 0,
   "mandatory_depends_on": null,
   "modified": "2021-02-01 08:33:53.241109",
   "modified_by": "Administrator",
   "name": "Stock Entry Detail-supplier_bag_no",
   "no_copy": 0,
   "non_negative": 0,
   "options": null,
   "owner": "Administrator",
   "parent": null,
   "parentfield": null,
   "parenttype": null,
   "permlevel": 0,
   "precision": "",
   "print_hide": 0,
   "print_hide_if_no_value": 0,
   "print_width": null,
   "read_only": 0,
   "read_only_depends_on": null,
   "report_hide": 0,
   "reqd": 0,
   "search_index": 0,
   "translatable": 1,
   "unique": 0,
   "width": null
  },
  {
   "_assign": null,
   "_comments": null,
   "_liked_by": null,
   "_user_tags": null,
   "allow_in_quick_entry": 0,
   "allow_on_submit": 0,
   "bold": 0,
   "collapsible": 0,
   "collapsible_depends_on": null,
   "columns": 0,
   "creation": "2021-02-01 08:33:53.555407",
   "default": null,
   "depends_on": null,
   "description": null,
   "docstatus": 0,
   "dt": "Stock Entry Detail",
   "fetch_from": null,
   "fetch_if_empty": 0,
   "fieldname": "analysis_required",
   "fieldtype": "Check",
   "hidden": 0,
   "hide_border": 0,
   "hide_days": 0,
   "hide_seconds": 0,
   "idx": 16,
   "ignore_user_permissions": 0,
   "ignore_xss_filter": 0,
   "in_global_search": 0,
   "in_list_view": 0,
   "in_preview": 0,
   "in_standard_filter": 0,
   "insert_after": "outpacking_rm",
   "label": "Analysis Required",
   "length": 0,
   "mandatory_depends_on": null,
   "modified": "2021-02-01 08:33:53.555407",
   "modified_by": "Administrator",
   "name": "Stock Entry Detail-analysis_required",
   "no_copy": 0,
   "non_negative": 0,
   "options": null,
   "owner": "Administrator",
   "parent": null,
   "parentfield": null,
   "parenttype": null,
   "permlevel": 0,
   "precision": "",
   "print_hide": 0,
   "print_hide_if_no_value": 0,
   "print_width": null,
   "read_only": 0,
   "read_only_depends_on": null,
   "report_hide": 0,
   "reqd": 0,
   "search_index": 0,
   "translatable": 0,
   "unique": 0,
   "width": null
  },
  {
   "_assign": null,
   "_comments": null,
   "_liked_by": null,
   "_user_tags": null,
   "allow_in_quick_entry": 0,
   "allow_on_submit": 0,
   "bold": 0,
   "collapsible": 0,
   "collapsible_depends_on": null,
   "columns": 0,
   "creation": "2021-11-12 00:47:43.455744",
   "default": null,
   "depends_on": null,
   "description": null,
   "docstatus": 0,
   "dt": "Stock Entry Detail",
   "fetch_from": null,
   "fetch_if_empty": 0,
   "fieldname": "rm_quality_inspection",
   "fieldtype": "Link",
   "hidden": 1,
   "hide_border": 0,
   "hide_days": 0,
   "hide_seconds": 0,
   "idx": 14,
   "ignore_user_permissions": 0,
   "ignore_xss_filter": 0,
   "in_global_search": 0,
   "in_list_view": 0,
   "in_preview": 0,
   "in_standard_filter": 0,
   "insert_after": "quality_inspection",
   "label": "RM Quality Inspection",
   "length": 0,
   "mandatory_depends_on": null,
   "modified": "2021-11-12 00:47:43.455744",
   "modified_by": "Administrator",
   "name": "Stock Entry Detail-rm_quality_inspection",
   "no_copy": 0,
   "non_negative": 0,
   "options": "Quality Inspection",
   "owner": "Administrator",
   "parent": null,
   "parentfield": null,
   "parenttype": null,
   "permlevel": 0,
   "precision": "",
   "print_hide": 0,
   "print_hide_if_no_value": 0,
   "print_width": null,
   "read_only": 1,
   "read_only_depends_on": null,
   "report_hide": 0,
   "reqd": 0,
   "search_index": 0,
   "translatable": 0,
   "unique": 0,
   "width": null
  },
  {
   "_assign": null,
   "_comments": null,
   "_liked_by": null,
   "_user_tags": null,
   "allow_in_quick_entry": 0,
   "allow_on_submit": 0,
   "bold": 0,
   "collapsible": 0,
   "collapsible_depends_on": null,
   "columns": 0,
   "creation": "2021-11-24 10:00:32.972363",
   "default": null,
   "depends_on": null,
   "description": null,
   "docstatus": 0,
   "dt": "Stock Entry Detail",
   "fetch_from": null,
   "fetch_if_empty": 0,
   "fieldname": "outpacking_rm",
   "fieldtype": "Check",
   "hidden": 0,
   "hide_border": 0,
   "hide_days": 0,
   "hide_seconds": 0,
   "idx": 15,
   "ignore_user_permissions": 0,
   "ignore_xss_filter": 0,
   "in_global_search": 0,
   "in_list_view": 0,
   "in_preview": 0,
   "in_standard_filter": 0,
   "insert_after": "rm_quality_inspection",
   "label": "Is Drum for Out-Packing",
   "length": 0,
   "mandatory_depends_on": null,
   "modified": "2021-11-24 10:00:32.972363",
   "modified_by": "Administrator",
   "name": "Stock Entry Detail-outpacking_rm",
   "no_copy": 0,
   "non_negative": 0,
   "options": null,
   "owner": "Administrator",
   "parent": null,
   "parentfield": null,
   "parenttype": null,
   "permlevel": 0,
   "precision": "",
   "print_hide": 0,
   "print_hide_if_no_value": 0,
   "print_width": null,
   "read_only": 0,
   "read_only_depends_on": null,
   "report_hide": 0,
   "reqd": 0,
   "search_index": 0,
   "translatable": 0,
   "unique": 0,
   "width": null
  }
 ],
 "custom_perms": [],
 "doctype": "Stock Entry Detail",
 "property_setters": [
  {
   "_assign": null,
   "_comments": null,
   "_liked_by": null,
   "_user_tags": null,
   "creation": "2021-01-08 18:07:20.357674",
   "default_value": null,
   "doc_type": "Stock Entry Detail",
   "docstatus": 0,
   "doctype_or_field": "DocField",
   "field_name": "batch_no",
   "idx": 0,
   "modified": "2021-01-05 13:19:49.773598",
   "modified_by": "Administrator",
   "name": "Stock Entry Detail-batch_no-in_list_view",
   "owner": "Administrator",
   "parent": null,
   "parentfield": null,
   "parenttype": null,
   "property": "in_list_view",
   "property_type": "Check",
   "row_name": null,
   "value": "1"
  },
  {
   "_assign": null,
   "_comments": null,
   "_liked_by": null,
   "_user_tags": null,
   "creation": "2021-01-08 18:07:20.294309",
   "default_value": null,
   "doc_type": "Stock Entry Detail",
   "docstatus": 0,
   "doctype_or_field": "DocField",
   "field_name": "quality_inspection",
   "idx": 0,
   "modified": "2021-01-05 13:19:17.933666",
   "modified_by": "Administrator",
   "name": "Stock Entry Detail-quality_inspection-in_list_view",
   "owner": "Administrator",
   "parent": null,
   "parentfield": null,
   "parenttype": null,
   "property": "in_list_view",
   "property_type": "Check",
   "row_name": null,
   "value": "1"
  },
  {
   "_assign": null,
   "_comments": null,
   "_liked_by": null,
   "_user_tags": null,
   "creation": "2021-01-08 18:07:20.225387",
   "default_value": null,
   "doc_type": "Stock Entry Detail",
   "docstatus": 0,
   "doctype_or_field": "DocField",
   "field_name": "t_warehouse",
   "idx": 0,
   "modified": "2021-01-05 13:19:17.736769",
   "modified_by": "Administrator",
   "name": "Stock Entry Detail-t_warehouse-in_list_view",
   "owner": "Administrator",
   "parent": null,
   "parentfield": null,
   "parenttype": null,
   "property": "in_list_view",
   "property_type": "Check",
   "row_name": null,
   "value": "0"
  },
  {
   "_assign": null,
   "_comments": null,
   "_liked_by": null,
   "_user_tags": null,
   "creation": "2021-01-08 18:07:20.153289",
   "default_value": null,
   "doc_type": "Stock Entry Detail",
   "docstatus": 0,
   "doctype_or_field": "DocField",
   "field_name": "s_warehouse",
   "idx": 0,
   "modified": "2021-01-05 13:19:17.460856",
   "modified_by": "Administrator",
   "name": "Stock Entry Detail-s_warehouse-in_list_view",
   "owner": "Administrator",
   "parent": null,
   "parentfield": null,
   "parenttype": null,
   "property": "in_list_view",
   "property_type": "Check",
   "row_name": null,
   "value": "0"
  },
  {
   "_assign": null,
   "_comments": null,
   "_liked_by": null,
   "_user_tags": null,
   "creation": "2021-01-08 18:07:18.649822",
   "default_value": null,
   "doc_type": "Stock Entry Detail",
   "docstatus": 0,
   "doctype_or_field": "DocField",
   "field_name": "barcode",
   "idx": 0,
   "modified": "2020-12-22 16:22:29.489538",
   "modified_by": "Administrator",
   "name": "Stock Entry Detail-barcode-hidden",
   "owner": "Administrator",
   "parent": null,
   "parentfield": null,
   "parenttype": null,
   "property": "hidden",
   "property_type": "Check",
   "row_name": null,
   "value": "0"
  }
 ],
 "sync_on_migrate": 1
}